django_tequila/__init__.py
django_tequila/admin.py
django_tequila/middleware.py
django_tequila/urls.py
django_tequila/django_backend/__init__.py
django_tequila/tequila_auth_views/__init__.py
django_tequila/tequila_client/__init__.py
django_tequila/tequila_client/client.py
django_tequila/tequila_client/config.py
django_tequila-3.3.0.dist-info/AUTHORS
django_tequila-3.3.0.dist-info/METADATA
django_tequila-3.3.0.dist-info/WHEEL
django_tequila-3.3.0.dist-info/top_level.txt
django_tequila-3.3.0.dist-info/RECORD
