Metadata-Version: 2.1
Name: django-tequila
Version: 3.3.0
Summary: A Tequila authentication backend for django
Home-page: https://github.com/epfl-idevelop/django-tequila
Author: Julien Delasoie
Author-email: julien.delasoie@epfl.ch
License: LGPLv3
Keywords: django,tequila,authentication
Platform: UNKNOWN
Classifier: Programming Language :: Python
Classifier: Development Status :: 5 - Production/Stable
Classifier: Environment :: Web Environment
Classifier: Intended Audience :: Developers
Classifier: License :: OSI Approved :: GNU Library or Lesser General Public License (LGPL)
Classifier: Operating System :: OS Independent
Classifier: Framework :: Django
Classifier: Topic :: Internet :: WWW/HTTP
Classifier: Topic :: System :: Systems Administration :: Authentication/Directory
